<?xml version="1.0" encoding="UTF-8"?>

<gating:Gating-ML
    xmlns:gating="http://www.isac-net.org/std/Gating-ML/v2.0/gating"
    xmlns:data-type="http://www.isac-net.org/std/Gating-ML/v2.0/datatypes">

    <gating:QuadrantGate gating:id="Quadrant2">
        <gating:divider gating:id="FSC" gating:compensation-ref="uncompensated">
            <data-type:fcs-dimension data-type:name="FSC-H" />
            <gating:value>28.0654</gating:value>
            <gating:value>70.02725</gating:value>
        </gating:divider>
        <gating:divider gating:id="SSC" gating:compensation-ref="uncompensated">
            <data-type:fcs-dimension data-type:name="SSC-H" />
            <gating:value>17.75</gating:value>
        </gating:divider>
        <gating:divider gating:id="FL1" gating:compensation-ref="uncompensated">
            <data-type:fcs-dimension data-type:name="FL1-H" />
            <gating:value>6.43567</gating:value>
        </gating:divider>
        <gating:Quadrant gating:id="FSCN-SSCN">
            <gating:position gating:divider_ref="FSC" gating:location="10" />
            <gating:position gating:divider_ref="SSC" gating:location="10" />
        </gating:Quadrant>
        <gating:Quadrant gating:id="FSCD-SSCN-FL1N">
            <gating:position gating:divider_ref="FSC" gating:location="30" />
            <gating:position gating:divider_ref="SSC" gating:location="10" />
            <gating:position gating:divider_ref="FL1" gating:location="5" />
        </gating:Quadrant>
        <gating:Quadrant gating:id="FSCP-SSCN-FL1N">
            <gating:position gating:divider_ref="FSC" gating:location="80" />
            <gating:position gating:divider_ref="SSC" gating:location="10" />
            <gating:position gating:divider_ref="FL1" gating:location="5" />
        </gating:Quadrant>
        <gating:Quadrant gating:id="FSCD-FL1P">
            <gating:position gating:divider_ref="FSC" gating:location="30" />
            <gating:position gating:divider_ref="FL1" gating:location="10" />
        </gating:Quadrant>
        <gating:Quadrant gating:id="FSCN-SSCP-FL1P">
            <gating:position gating:divider_ref="FSC" gating:location="10" />
            <gating:position gating:divider_ref="SSC" gating:location="20" />
            <gating:position gating:divider_ref="FL1" gating:location="15" />
        </gating:Quadrant>
    </gating:QuadrantGate>
</gating:Gating-ML>
